color_operations/colorspace.cpython-312-darwin.so
color_operations/colorspace.pyx
color_operations/__init__.py
color_operations/operations.py
color_operations/utils.py
color_operations-0.2.0.dist-info/RECORD
color_operations-0.2.0.dist-info/WHEEL
color_operations-0.2.0.dist-info/top_level.txt
color_operations-0.2.0.dist-info/METADATA
color_operations-0.2.0.dist-info/licenses/LICENSE
